Workbook

Sheet Summary
A1: Delivery and margin review
A2: Period | B2: 2026-08
A3: Run id | B3: delivery-review-2026-08
A4: Scoring model version | B4: v1.0
A6: Portfolio
A7: Engagements in the book | B7: =COUNT(Engagements!A2:A19)
A8: Examined in detail | B8: =COUNTIF(Engagements!T2:T19,"yes")
A9: Ceiling hours | B9: =SUM(Engagements!J2:J19)
A10: Hours to date | B10: =SUM(Engagements!K2:K19)
A11: Ceiling amount | B11: =SUM(Engagements!M2:M19)
A12: Over their ceiling | B12: =COUNTIF(Engagements!L2:L19,">1")
A13: Above 70% burn | B13: =COUNTIF(Engagements!L2:L19,">0.7")
A14: Not in the green band | B14: =COUNTIF(Engagements!Q2:Q19,"<>green")
A15: Above 70% person concentration | B15: =COUNTIF(Engagements!N2:N19,">70")
A16: Projections reported low confidence | B16: =COUNTIF(Engagements!AA2:AA19,"low")
A17: Exceptions raised | B17: =COUNT(Exceptions!A2:A200)
A19: Portfolio, as the tools measured it
A20: Active engagements | B20: 18
A21: Clients | B21: 11
A22: In the green band | B22: 13
A23: Ceiling hours | B23: 44390
A24: Hours to date | B24: 25882.1
A25: Portfolio burn | B25: 58.3
A26: Revenue to date | B26: 8081943.6
A27: Cost to date | B27: 3169258.7
A28: Blended margin | B28: 60.8
A29: Mean health score | B29: 83.4
A30: Blended margin, movement vs prior month | B30: -2.9
A31: Mean health score, movement vs prior month | B31: -1.2
A32: Hours to date, movement vs prior month | B32: 2737.7
A34: Reporting coverage
A35: Weeks below the coverage floor | B35: 1
A36: Lowest weekly reporting coverage | B36: 16.7

Sheet Engagements
A1: engagement_id | B1: client_name | C1: name | D1: sow_ref | E1: fee_type | F1: status | G1: start_date | H1: end_date | I1: days_remaining | J1: ceiling_hours | K1: hours_to_date | L1: burn_pct | M1: ceiling_amount | N1: person_concentration_pct | O1: people_count | P1: health_score | Q1: health_band | R1: score_delta_vs_prior_period | S1: top_risk_factor | T1: examined | U1: hours_remaining | V1: weekly_run_rate_4wk | W1: weeks_counted | X1: weeks_with_no_hours | Y1: projected_total_hours | Z1: projected_overrun_pct | AA1: projection_confidence | AB1: confidence_reason | AC1: run_rate_vs_baseline_pct | AD1: days_since_last_entry | AE1: late_entry_pct | AF1: invoiced | AG1: paid | AH1: wip_unbilled | AI1: cost_to_date | AJ1: billable_value_to_date | AK1: margin_pct | AL1: realisation_pct | AM1: dso_days | AN1: dso_baseline_days | AO1: payment_behaviour_change_pct
A2: 2 | B2: Oakhaven Logistics Collective | C2: Credit Risk Migration | D2: SOW-2026-002 | E2: fixed | F2: active | G2: 2026-01-28 | H2: 2026-08-21 | I2: 0 | J2: 1980 | K2: 575.9 | L2: =IF(N(J2)>0,K2/J2,"") | M2: 420591.6 | N2: 55.5 | O2: 3 | P2: 99.7 | Q2: green | R2: -0.3 | S2: payment_behaviour | T2: yes | U2: 1404.1 | V2: 17.55 | W2: 4 | X2: 0 | Y2: 575.9 | Z2: =IF(AND(N(J2)>0,Y2<>""),MAX(0,Y2-J2)/J2,"") | AA2: high | AB2: 4 readable weeks with time logged in every one, 0.0% of entries filed after the period closed | AC2: -32 | AD2: 0 | AE2: 0 | AF2: 280394.4 | AG2: 280394.4 | AH2: -156504.3 | AI2: 70481.3 | AJ2: 123890.1 | AK2: =IF(AI2="","",IF(E2="fixed",IF(N(M2)>0,(M2-AI2)/M2,""),IF(N(AJ2)>0,(AJ2-AI2)/AJ2,""))) | AL2: 86.8 | AM2: 29.5 | AN2: 29 | AO2: 1.7
A3: 3 | B3: Ashcombe Health Partners | C3: Revenue Assurance Optimisation | D3: SOW-2026-003 | E3: time_and_materials | F3: active | G3: 2026-01-09 | H3: 2026-10-31 | I3: 61 | J3: 940 | K3: 642.1 | L3: =IF(N(J3)>0,K3/J3,"") | M3: 232180 | N3: 46.2 | O3: 3 | P3: 98.3 | Q3: green | R3: -0.9 | S3: burn_trajectory | T3: no | Z3: =IF(AND(N(J3)>0,Y3<>""),MAX(0,Y3-J3)/J3,"") | AK3: =IF(AI3="","",IF(E3="fixed",IF(N(M3)>0,(M3-AI3)/M3,""),IF(N(AJ3)>0,(AJ3-AI3)/AJ3,"")))
A4: 5 | B4: Pentland Media Group | C4: Procurement Modernisation | D4: SOW-2026-005 | E4: fixed | F4: active | G4: 2026-01-31 | H4: 2026-10-10 | I4: 40 | J4: 2690 | K4: 1751.5 | L4: =IF(N(J4)>0,K4/J4,"") | M4: 133038.43 | N4: 24.8 | O4: 5 | P4: 69 | Q4: amber | R4: -11.2 | S4: margin | T4: yes | U4: 938.5 | V4: 68.88 | W4: 4 | X4: 0 | Y4: 2145.1 | Z4: =IF(AND(N(J4)>0,Y4<>""),MAX(0,Y4-J4)/J4,"") | AA4: high | AB4: 4 readable weeks with time logged in every one, 3.4% of entries filed after the period closed | AC4: 37.2 | AD4: 0 | AE4: 3.4 | AF4: 83149.02 | AG4: 49889.41 | AH4: 247112.18 | AI4: 156515.8 | AJ4: 330261.2 | AK4: =IF(AI4="","",IF(E4="fixed",IF(N(M4)>0,(M4-AI4)/M4,""),IF(N(AJ4)>0,(AJ4-AI4)/AJ4,""))) | AL4: 87 | AM4: 44 | AN4: 41.1 | AO4: 6.9
A5: 7 | B5: Braemar Retail Corporation | C5: Revenue Assurance Discovery | D5: SOW-2026-007 | E5: time_and_materials | F5: active | G5: 2026-02-19 | H5: 2027-02-27 | I5: 180 | J5: 1480 | K5: 672.5 | L5: =IF(N(J5)>0,K5/J5,"") | M5: 393680 | N5: 45 | O5: 3 | P5: 100 | Q5: green | R5: 31.2 | T5: no | Z5: =IF(AND(N(J5)>0,Y5<>""),MAX(0,Y5-J5)/J5,"") | AK5: =IF(AI5="","",IF(E5="fixed",IF(N(M5)>0,(M5-AI5)/M5,""),IF(N(AJ5)>0,(AJ5-AI5)/AJ5,"")))
A6: 8 | B6: Braemar Retail Corporation | C6: Regulatory Reporting Programme | D6: SOW-2025-008 | E6: fixed | F6: active | G6: 2025-11-16 | H6: 2027-05-12 | I6: 254 | J6: 1020 | K6: 1336.4 | L6: =IF(N(J6)>0,K6/J6,"") | M6: 274176 | N6: 48.9 | O6: 4 | P6: 53.5 | Q6: amber | R6: -3.8 | S6: burn_trajectory | T6: yes | U6: -316.4 | V6: 32.15 | W6: 4 | X6: 0 | Y6: 2503 | Z6: =IF(AND(N(J6)>0,Y6<>""),MAX(0,Y6-J6)/J6,"") | AA6: high | AB6: 4 readable weeks with time logged in every one, 2.1% of entries filed after the period closed | AC6: -1.7 | AD6: 3 | AE6: 2.1 | AF6: 42180.92 | AG6: 42180.92 | AH6: 351264.68 | AI6: 206372.8 | AJ6: 393445.6 | AK6: =IF(AI6="","",IF(E6="fixed",IF(N(M6)>0,(M6-AI6)/M6,""),IF(N(AJ6)>0,(AJ6-AI6)/AJ6,""))) | AL6: 90 | AM6: 24.3 | AN6: 25.3 | AO6: -4
A7: 9 | B7: Northfield Municipal Group | C7: Pricing Modernisation | D7: SOW-2026-009 | E7: fixed | F7: active | G7: 2026-01-23 | H7: 2026-11-10 | I7: 71 | J7: 780 | K7: 971.2 | L7: =IF(N(J7)>0,K7/J7,"") | M7: 241737.6 | N7: 54.1 | O7: 2 | P7: 59.5 | Q7: amber | R7: -5.5 | S7: burn_trajectory | T7: yes | U7: -191.2 | V7: 41.73 | W7: 4 | X7: 0 | Y7: 1394.4 | Z7: =IF(AND(N(J7)>0,Y7<>""),MAX(0,Y7-J7)/J7,"") | AA7: high | AB7: 4 readable weeks with time logged in every one, 3.1% of entries filed after the period closed | AC7: 12.5 | AD7: 0 | AE7: 3.1 | AF7: 136634.29 | AG7: 136634.29 | AH7: 172915.71 | AI7: 160725.6 | AJ7: 309550 | AK7: =IF(AI7="","",IF(E7="fixed",IF(N(M7)>0,(M7-AI7)/M7,""),IF(N(AJ7)>0,(AJ7-AI7)/AJ7,""))) | AL7: 87 | AM7: 32.8 | AN7: 31.3 | AO7: 4.5
A8: 11 | B8: Lowmarsh Retail Partners | C8: Inventory Modernisation | D8: SOW-2025-011 | E8: fixed | F8: active | G8: 2025-10-11 | H8: 2027-05-02 | I8: 244 | J8: 4940 | K8: 2821 | L8: =IF(N(J8)>0,K8/J8,"") | M8: 1332713.2 | N8: 44.7 | O8: 3 | P8: 73.1 | Q8: green | R8: -6.6 | S8: burn_trajectory | T8: no | Z8: =IF(AND(N(J8)>0,Y8<>""),MAX(0,Y8-J8)/J8,"") | AK8: =IF(AI8="","",IF(E8="fixed",IF(N(M8)>0,(M8-AI8)/M8,""),IF(N(AJ8)>0,(AJ8-AI8)/AJ8,"")))
A9: 12 | B9: Stonebridge Energy Group | C9: Credit Risk Programme | D9: SOW-2026-012 | E9: time_and_materials | F9: active | G9: 2026-01-14 | H9: 2026-09-24 | I9: 24 | J9: 1480 | K9: 998.4 | L9: =IF(N(J9)>0,K9/J9,"") | M9: 478040 | N9: 85.4 | O9: 2 | P9: 99.9 | Q9: green | R9: 0.4 | S9: payment_behaviour | T9: yes | U9: 481.6 | V9: 34.03 | W9: 4 | X9: 0 | Y9: 1115.1 | Z9: =IF(AND(N(J9)>0,Y9<>""),MAX(0,Y9-J9)/J9,"") | AA9: high | AB9: 4 readable weeks with time logged in every one, 9.9% of entries filed after the period closed | AC9: 1.3 | AD9: 0 | AE9: 9.9 | AF9: 261087.5 | AG9: 207099.5 | AH9: 21938.5 | AI9: 138190.2 | AJ9: 283026 | AK9: =IF(AI9="","",IF(E9="fixed",IF(N(M9)>0,(M9-AI9)/M9,""),IF(N(AJ9)>0,(AJ9-AI9)/AJ9,""))) | AL9: 88.7 | AM9: 39.8 | AN9: 39.7 | AO9: 0.4
A10: 13 | B10: Ashcombe Health Partners | C10: Payments Assessment | D10: SOW-2025-013 | E10: time_and_materials | F10: active | G10: 2025-09-28 | H10: 2026-12-08 | I10: 99 | J10: 3200 | K10: 2097.5 | L10: =IF(N(J10)>0,K10/J10,"") | M10: 812800 | N10: 63.6 | O10: 3 | P10: 89.1 | Q10: green | R10: -0.2 | S10: burn_trajectory | T10: no | Z10: =IF(AND(N(J10)>0,Y10<>""),MAX(0,Y10-J10)/J10,"") | AK10: =IF(AI10="","",IF(E10="fixed",IF(N(M10)>0,(M10-AI10)/M10,""),IF(N(AJ10)>0,(AJ10-AI10)/AJ10,"")))
A11: 15 | B11: Ashcombe Health Partners | C11: Workforce Planning Programme | D11: SOW-2025-015 | E11: time_and_materials | F11: active | G11: 2025-11-04 | H11: 2026-10-16 | I11: 46 | J11: 3540 | K11: 2694.5 | L11: =IF(N(J11)>0,K11/J11,"") | M11: 1069080 | N11: 50.2 | O11: 4 | P11: 94.4 | Q11: green | R11: 10.2 | S11: burn_trajectory | T11: yes | U11: 845.5 | V11: 71.18 | W11: 4 | X11: 0 | Y11: 3162.2 | Z11: =IF(AND(N(J11)>0,Y11<>""),MAX(0,Y11-J11)/J11,"") | AA11: high | AB11: 4 readable weeks with time logged in every one, 6.5% of entries filed after the period closed | AC11: -21.2 | AD11: 0 | AE11: 6.5 | AF11: 453254.3 | AG11: 372346 | AH11: 98811.1 | AI11: 272353.4 | AJ11: 552065.4 | AK11: =IF(AI11="","",IF(E11="fixed",IF(N(M11)>0,(M11-AI11)/M11,""),IF(N(AJ11)>0,(AJ11-AI11)/AJ11,""))) | AL11: 88.8 | AM11: 36.7 | AN11: 35.5 | AO11: 3.4
A12: 16 | B12: Braemar Retail Corporation | C12: Field Operations Rollout | D12: SOW-2025-016 | E12: time_and_materials | F12: active | G12: 2025-09-01 | H12: 2027-03-09 | I12: 190 | J12: 7980 | K12: 2552.1 | L12: =IF(N(J12)>0,K12/J12,"") | M12: 1955100 | N12: 41.7 | O12: 3 | P12: 100 | Q12: green | R12: 0.2 | T12: no | Z12: =IF(AND(N(J12)>0,Y12<>""),MAX(0,Y12-J12)/J12,"") | AK12: =IF(AI12="","",IF(E12="fixed",IF(N(M12)>0,(M12-AI12)/M12,""),IF(N(AJ12)>0,(AJ12-AI12)/AJ12,"")))
A13: 18 | B13: Thornbury Retail Partners | C13: Payments Modernisation | D13: SOW-2025-018 | E13: fixed | F13: active | G13: 2025-12-04 | H13: 2026-12-04 | I13: 95 | J13: 820 | K13: 564.5 | L13: =IF(N(J13)>0,K13/J13,"") | M13: 217906.8 | N13: 53.2 | O13: 3 | P13: 94.1 | Q13: green | R13: -5.7 | S13: burn_trajectory | T13: no | Z13: =IF(AND(N(J13)>0,Y13<>""),MAX(0,Y13-J13)/J13,"") | AK13: =IF(AI13="","",IF(E13="fixed",IF(N(M13)>0,(M13-AI13)/M13,""),IF(N(AJ13)>0,(AJ13-AI13)/AJ13,"")))
A14: 19 | B14: Thornbury Retail Partners | C14: Grid Analytics Assessment | D14: SOW-2025-019 | E14: time_and_materials | F14: active | G14: 2025-12-03 | H14: 2026-10-10 | I14: 40 | J14: 940 | K14: 816.8 | L14: =IF(N(J14)>0,K14/J14,"") | M14: 262260 | N14: 59.5 | O14: 2 | P14: 76.6 | Q14: green | R14: -12.2 | S14: burn_trajectory | T14: yes | U14: 123.2 | V14: 29.88 | W14: 4 | X14: 0 | Y14: 987.5 | Z14: =IF(AND(N(J14)>0,Y14<>""),MAX(0,Y14-J14)/J14,"") | AA14: high | AB14: 4 readable weeks with time logged in every one, 7.5% of entries filed after the period closed | AC14: 36.3 | AD14: 0 | AE14: 7.5 | AF14: 189126.6 | AG14: 189126.6 | AH14: 30225 | AI14: 106100 | AJ14: 219351.6 | AK14: =IF(AI14="","",IF(E14="fixed",IF(N(M14)>0,(M14-AI14)/M14,""),IF(N(AJ14)>0,(AJ14-AI14)/AJ14,""))) | AL14: 86.4 | AM14: 29.7 | AN14: 30.8 | AO14: -3.7
A15: 20 | B15: Quarrymoor Transit Partners | C15: Inventory Implementation | D15: SOW-2025-020 | E15: fixed | F15: active | G15: 2025-11-30 | H15: 2027-04-16 | I15: 228 | J15: 4840 | K15: 2720.7 | L15: =IF(N(J15)>0,K15/J15,"") | M15: 1154243.2 | N15: 33 | O15: 6 | P15: 64 | Q15: amber | R15: 0.8 | S15: burn_trajectory | T15: yes | U15: 2119.3 | V15: 110.78 | W15: 4 | X15: 0 | Y15: 6328.8 | Z15: =IF(AND(N(J15)>0,Y15<>""),MAX(0,Y15-J15)/J15,"") | AA15: high | AB15: 4 readable weeks with time logged in every one, 7.8% of entries filed after the period closed | AC15: 17.8 | AD15: 0 | AE15: 7.8 | AF15: 355151.75 | AG15: 355151.75 | AH15: 255780.05 | AI15: 288157 | AJ15: 610931.8 | AK15: =IF(AI15="","",IF(E15="fixed",IF(N(M15)>0,(M15-AI15)/M15,""),IF(N(AJ15)>0,(AJ15-AI15)/AJ15,""))) | AL15: 89.1 | AM15: 55 | AN15: 51.7 | AO15: 6.5
A16: 22 | B16: Fernhollow Financial Trust | C16: Billing Platform Assessment | D16: SOW-2026-022 | E16: time_and_materials | F16: active | G16: 2026-02-19 | H16: 2027-01-25 | I16: 147 | J16: 1520 | K16: 895.2 | L16: =IF(N(J16)>0,K16/J16,"") | M16: 443840 | N16: 33.1 | O16: 4 | P16: 68.9 | Q16: amber | R16: -7.2 | S16: burn_trajectory | T16: yes | U16: 624.8 | V16: 37.78 | W16: 4 | X16: 0 | Y16: 1688.5 | Z16: =IF(AND(N(J16)>0,Y16<>""),MAX(0,Y16-J16)/J16,"") | AA16: high | AB16: 4 readable weeks with time logged in every one, 3.4% of entries filed after the period closed | AC16: 3.3 | AD16: 0 | AE16: 3.4 | AF16: 197232.6 | AG16: 110441.3 | AH16: 31998.2 | AI16: 115100.6 | AJ16: 229230.8 | AK16: =IF(AI16="","",IF(E16="fixed",IF(N(M16)>0,(M16-AI16)/M16,""),IF(N(AJ16)>0,(AJ16-AI16)/AJ16,""))) | AL16: 90.9 | AM16: 46.2 | AN16: 44.1 | AO16: 4.7
A17: 23 | B17: Fernhollow Financial Trust | C17: Asset Register Assessment | D17: SOW-2025-023 | E17: fixed | F17: active | G17: 2025-12-30 | H17: 2027-01-11 | I17: 133 | J17: 1840 | K17: 695.4 | L17: =IF(N(J17)>0,K17/J17,"") | M17: 455731.2 | N17: 55.7 | O17: 2 | P17: 99.3 | Q17: green | R17: -0.7 | S17: payment_behaviour | T17: no | Z17: =IF(AND(N(J17)>0,Y17<>""),MAX(0,Y17-J17)/J17,"") | AK17: =IF(AI17="","",IF(E17="fixed",IF(N(M17)>0,(M17-AI17)/M17,""),IF(N(AJ17)>0,(AJ17-AI17)/AJ17,"")))
A18: 25 | B18: Stonebridge Energy Group | C18: Billing Platform Implementation | D18: SOW-2025-025 | E18: time_and_materials | F18: active | G18: 2025-11-11 | H18: 2026-10-25 | I18: 55 | J18: 2440 | K18: 1967.8 | L18: =IF(N(J18)>0,K18/J18,"") | M18: 688080 | N18: 53.7 | O18: 3 | P18: 76.6 | Q18: green | R18: -9.4 | S18: reporting_gap | T18: yes | U18: 472.2 | V18: 22.53 | W18: 4 | X18: 2 | Y18: 2144.8 | Z18: =IF(AND(N(J18)>0,Y18<>""),MAX(0,Y18-J18)/J18,"") | AA18: low | AB18: 2 of the trailing 4 readable weeks have no time logged against this engagement | AC18: -46.6 | AD18: 24 | AE18: 0 | AF18: 441859 | AG18: 403089 | AH18: 8091.5 | AI18: 224191.7 | AJ18: 449950.5 | AK18: =IF(AI18="","",IF(E18="fixed",IF(N(M18)>0,(M18-AI18)/M18,""),IF(N(AJ18)>0,(AJ18-AI18)/AJ18,""))) | AL18: 87.4 | AM18: 39.8 | AN18: 39.7 | AO18: 0.4
A19: 29 | B19: Merrivale Maritime Corporation | C19: Grid Analytics Integration | D19: SOW-2026-029 | E19: fixed | F19: active | G19: 2026-01-26 | H19: 2026-12-26 | I19: 117 | J19: 1960 | K19: 1108.6 | L19: =IF(N(J19)>0,K19/J19,"") | M19: 482904.8 | N19: 37.1 | O19: 5 | P19: 85.6 | Q19: green | R19: -1.3 | S19: burn_trajectory | T19: no | Z19: =IF(AND(N(J19)>0,Y19<>""),MAX(0,Y19-J19)/J19,"") | AK19: =IF(AI19="","",IF(E19="fixed",IF(N(M19)>0,(M19-AI19)/M19,""),IF(N(AJ19)>0,(AJ19-AI19)/AJ19,"")))

Sheet Time Detail
A1: engagement_id | B1: engagement_name | C1: week_start | D1: hours | E1: billable_hours | F1: cost | G1: billable_value | H1: entry_count | I1: pct_active_reporting | J1: firm_wide_gap
A2: 2 | B2: Credit Risk Migration | C2: 2026-08-03 | D2: 10 | E2: 7.8 | F2: 1157.1 | G2: 1974.2 | H2: 11 | I2: 100 | J2: FALSE
A3: 2 | B3: Credit Risk Migration | C3: 2026-08-17 | D3: 23.9 | E3: 21.6 | F3: 2865.5 | G3: 5359.6 | H3: 22 | I3: 94.4 | J3: FALSE
A4: 3 | B4: Revenue Assurance Optimisation | C4: 2026-08-03 | D4: 19.8 | E4: 19.5 | F4: 3060.9 | G4: 6409.1 | H4: 17 | I4: 100 | J4: FALSE
A5: 3 | B5: Revenue Assurance Optimisation | C5: 2026-08-17 | D5: 15.4 | E5: 15.4 | F5: 2522.2 | G5: 5498.4 | H5: 11 | I5: 94.4 | J5: FALSE
A6: 3 | B6: Revenue Assurance Optimisation | C6: 2026-08-24 | D6: 25.7 | E6: 23 | F6: 3395.1 | G6: 6896.5 | H6: 24 | I6: 94.1 | J6: FALSE
A7: 3 | B7: Revenue Assurance Optimisation | C7: 2026-08-31 | D7: 7 | E7: 6.6 | F7: 1097 | G7: 2276.3 | H7: 7 | I7: 76.5 | J7: FALSE
A8: 5 | B8: Procurement Modernisation | C8: 2026-08-03 | D8: 40.8 | E8: 35.1 | F8: 4130.5 | G8: 7844 | H8: 37 | I8: 100 | J8: FALSE
A9: 5 | B9: Procurement Modernisation | C9: 2026-08-10 | D9: 214.7 | E9: 187.1 | F9: 22176.3 | G9: 45110.1 | H9: 186 | I9: 16.7 | J9: TRUE
A10: 5 | B10: Procurement Modernisation | C10: 2026-08-17 | D10: 65 | E10: 47.6 | F10: 6377.2 | G10: 10605.3 | H10: 51 | I10: 94.4 | J10: FALSE
A11: 5 | B11: Procurement Modernisation | C11: 2026-08-24 | D11: 95.9 | E11: 91 | F11: 9038.2 | G11: 20318 | H11: 86 | I11: 94.1 | J11: FALSE
A12: 5 | B12: Procurement Modernisation | C12: 2026-08-31 | D12: 19.1 | E12: 14.4 | F12: 1878.2 | G12: 3463 | H12: 17 | I12: 76.5 | J12: FALSE
A13: 7 | B13: Revenue Assurance Discovery | C13: 2026-08-03 | D13: 8.8 | E13: 8.8 | F13: 1612.6 | G13: 3230.7 | H13: 10 | I13: 100 | J13: FALSE
... A76: 30 | B76: Asset Register Migration | C76: 2026-08-31 | D76: 11.2 | E76: 6.8 | F76: 919.2 | G76: 1306.5 | H76: 11 | I76: 76.5 | J76: FALSE

Sheet Exceptions
A1: engagement_id | B1: flag | C1: triggers | D1: situation | E1: cause | F1: recommended_action | G1: decision_owner
A2: 5 | B2: NEEDS REVIEW | C2: fixed fee below the margin floor; margin failing, burn healthy | D2: Fixed-fee engagement at -17.6% margin, against a floor of 15%. Margin is -17.6% while burn is 65.1% of the 2,690.0 hour ceiling. The two figures disagree and the data does not say which is the operative one. | E2: not determinable from available data | F2: Take the fixed-fee position to a scope and pricing conversation with the client before the 40 remaining contract days are used: decide whether remaining scope is delivered at the agreed fee, re-priced, or reduced. Engagement lead to decide, with the partner on the pricing question. | G2: engagement lead
A3: 8 | B3: RED | C3: projected overrun, high confidence; burn above 90% with duration remaining | D3: Projected overrun is 145.4% against a ceiling of 1,020.0 hours, at high projection confidence. Burn is 131.0% of a 1,020.0 hour ceiling with 254 of 542 contract days remaining. | E3: not determinable from available data | F3: Hours are 316.4 past the 1,020.0 hour ceiling with 254 contract days remaining. Decide whether to stop work at the ceiling or raise a change order for the remaining scope, and confirm the client position on the hours already delivered past it. Engagement lead to decide. | G3: engagement lead
A4: 9 | B4: RED | C4: projected overrun, high confidence; burn above 90% with duration remaining | D4: Projected overrun is 78.8% against a ceiling of 780.0 hours, at high projection confidence. Burn is 124.5% of a 780.0 hour ceiling with 71 of 291 contract days remaining. | E4: not determinable from available data | F4: Hours are 191.2 past the 780.0 hour ceiling with 71 contract days remaining. Decide whether to raise a change order or close out at the ceiling. Engagement lead to decide. | G4: engagement lead
A5: 12 | B5: NEEDS REVIEW | C5: concentration above median fee | D5: One person is 85.4% of hours on an engagement of 478,040, above the median fee. 2 people have logged time. | E5: not determinable from available data | F5: None. This trigger is a reason to look, not a decision to take. | G5: engagement lead
A6: 20 | B6: RED | C6: projected overrun, high confidence | D6: Projected overrun is 30.8% against a ceiling of 4,840.0 hours, at high projection confidence. | E6: not determinable from available data | F6: Projection at the current run rate exceeds the 4,840.0 hour ceiling by 30.8% with 228 contract days remaining. Decide whether the run rate is reduced, the scope trimmed, or a change order raised now rather than at the ceiling. Engagement lead to decide. | G6: engagement lead
A7: 22 | B7: RED | C7: projected overrun, high confidence | D7: Projected overrun is 11.1% against a ceiling of 1,520.0 hours, at high projection confidence. | E7: not determinable from available data | F7: Projection at the current run rate exceeds the 1,520.0 hour ceiling by 11.1% with 147 contract days remaining. Decide whether to re-plan the remaining scope or raise a change order. Engagement lead to decide. | G7: engagement lead
A8: 25 | B8: RED | C8: no time logged for 14 days | D8: No time has been logged for 24 days and the engagement is still active. Absent data is not evidence of completion. | E8: not determinable from available data | F8: Confirm with the delivery team whether work is ongoing and timesheets are outstanding, or whether delivery has in fact stopped; the absence of entries does not distinguish the two. Once known, decide whether the engagement status is changed. Engagement lead to decide. | G8: engagement lead

Sheet Data Quality
A1: Record quality — entries in the period
A2: Time entries in the period | B2: 2774 | C2: entry_count
A3: Filed after the period closed | B3: 160 | C3: late_entries
A4: Filed late, as a percentage | B4: 5.8 | C4: late_entry_pct
A5: No billable flag set | B5: 2 | C5: null_billable
A6: Redundant rows: same person, engagement, day and hours | B6: 1 | C6: suspected_duplicates
A7: Distinct duplicate groups | B7: 1 | C7: duplicate_groups
A9: Reporting coverage by week
A10: week_start | B10: week_end | C10: engagements_active | D10: engagements_reporting | E10: pct_active_reporting | F10: firm_wide_gap
A11: 2026-07-27 | B11: 2026-08-02 | C11: 18 | D11: 18 | E11: 100 | F11: FALSE
A12: 2026-08-03 | B12: 2026-08-09 | C12: 18 | D12: 18 | E12: 100 | F12: FALSE
A13: 2026-08-10 | B13: 2026-08-16 | C13: 18 | D13: 3 | E13: 16.7 | F13: TRUE
A14: 2026-08-17 | B14: 2026-08-23 | C14: 18 | D14: 17 | E14: 94.4 | F14: FALSE
A15: 2026-08-24 | B15: 2026-08-30 | C15: 17 | D15: 16 | E15: 94.1 | F15: FALSE
A16: 2026-08-31 | B16: 2026-09-06 | C16: 17 | D16: 13 | E16: 76.5 | F16: FALSE
A18: Data notes
A19: Week of 2026-08-10: 16.7% of active engagements filed time, below the 60% coverage floor. This week is a filing artifact. It is excluded from every run rate and projection in this workbook, and delivery for the week cannot be measured from the data.
A21: Projections reported with low confidence
A22: engagement_id | B22: projection_confidence | C22: confidence_reason
A23: 25 | B23: low | C23: 2 of the trailing 4 readable weeks have no time logged against this engagement
